rpcudp/__init__.py
rpcudp/exceptions.py
rpcudp/protocol.py
rpcudp-5.0.0.dist-info/METADATA
rpcudp-5.0.0.dist-info/WHEEL
rpcudp-5.0.0.dist-info/licenses/LICENSE
rpcudp-5.0.0.dist-info/RECORD
