Metadata-Version: 2.4
Name: rpcudp
Version: 5.0.0
Summary: Asynchronous RPC via UDP
Project-URL: Homepage, https://github.com/bmuller/rpcudp
Project-URL: Issues, https://github.com/bmuller/rpcudp/issues
Author-email: Brian Muller <bamuller@gmail.com>
License-File: LICENSE
Classifier: Development Status :: 5 - Production/Stable
Classifier: Intended Audience :: Developers
Classifier: License :: OSI Approved :: MIT License
Classifier: Operating System :: OS Independent
Classifier: Programming Language :: Python
Classifier: Programming Language :: Python :: 3
Classifier: Topic :: Software Development :: Libraries :: Python Modules
Requires-Python: >=3.9
Requires-Dist: u-msgpack-python>=2.6
